{
  "project_info": {
    "project_number": "40904701048",
    "firebase_url": "https://cabrider-258bd-default-rtdb.europe-west1.firebasedatabase.app",
    "project_id": "cabrider-258bd",
    "storage_bucket": "cabrider-258bd.appspot.com"
  },
  "client": [
    {
      "client_info": {
        "mobilesdk_app_id": "1:40904701048:android:a0f71c260169d9bcf7298d",
        "android_client_info": {
          "package_name": "com.pedromsluz.cab_rider"
        }
      },
      "oauth_client": [
        {
          "client_id": "40904701048-3lnf13jtipepv54debr6vbree754kstk.apps.googleusercontent.com",
          "client_type": 3
        }
      ],
      "api_key": [
        {
          "current_key": "AIzaSyB-sJ0H2OWVKNsCpyLz4BYOlSLp28uwK4E"
        }
      ],
      "services": {
        "appinvite_service": {
          "other_platform_oauth_client": [
            {
              "client_id": "40904701048-3lnf13jtipepv54debr6vbree754kstk.apps.googleusercontent.com",
              "client_type": 3
            }
          ]
        }
      }
    }
  ],
  "configuration_version": "1"
}